{"expireTime":9007200879115572000,"key":"transformer-remark-markdown-html-ast-448734b7086c8fb10764519aed04187d-gatsby-remark-external-linksgatsby-remark-imagesgatsby-remark-code-titlesgatsby-remark-prismjs-","val":{"type":"root","children":[{"type":"element","tagName":"p","properties":{},"children":[{"type":"text","value":"Github Profile Readme (Who am I?) with integrated automatic blog post github action.","position":{"start":{"line":2,"column":1,"offset":1},"end":{"line":2,"column":85,"offset":85}}}],"position":{"start":{"line":2,"column":1,"offset":1},"end":{"line":2,"column":85,"offset":85}}}],"position":{"start":{"line":1,"column":1,"offset":0},"end":{"line":3,"column":1,"offset":86}}}}